commonlib/__init__.py
commonlib/colour.py
commonlib/debugger.py
commonlib/dependency.py
commonlib/files.py
commonlib/frozen.py
commonlib/main.py
commonlib/path.py
commonlib/srb_bank.py
commonlib/srb_json.py
commonlib/system.py
commonlib/tabular.py
commonlib/util.py
srb_lib_004/__init__.py
srb_lib_004/colour.py
srb_lib_004/debugger.py
srb_lib_004/dependency.py
srb_lib_004/files.py
srb_lib_004/frozen.py
srb_lib_004/main.py
srb_lib_004/path.py
srb_lib_004/srb_bank.py
srb_lib_004/srb_json.py
srb_lib_004/system.py
srb_lib_004/tabular.py
srb_lib_004/util.py
srb_lib_004-0.0.1.dist-info/DESCRIPTION.rst
srb_lib_004-0.0.1.dist-info/METADATA
srb_lib_004-0.0.1.dist-info/RECORD
srb_lib_004-0.0.1.dist-info/WHEEL
srb_lib_004-0.0.1.dist-info/entry_points.txt
srb_lib_004-0.0.1.dist-info/metadata.json
srb_lib_004-0.0.1.dist-info/top_level.txt
srblib/__init__.py
srblib/colour.py
srblib/debugger.py
srblib/dependency.py
srblib/files.py
srblib/frozen.py
srblib/main.py
srblib/path.py
srblib/srb_bank.py
srblib/srb_json.py
srblib/system.py
srblib/tabular.py
srblib/util.py
