Metadata-Version: 2.0
Name: srb-lib-004
Version: 0.0.1
Summary: A python library by srb
Home-page: http://github.com/srbcheema1/srb_lib_004
Author: Sarbjit Singh
Author-email: srbcheema1@gmail.com
License: MIT License
Platform: UNKNOWN
Classifier: Operating System :: POSIX :: Linux
Classifier: License :: OSI Approved :: MIT License
Classifier: Programming Language :: Python :: 3.5
Requires-Dist: pandas
Requires-Dist: terminaltables
Requires-Dist: xlwt
Requires-Dist: xlrd
